{
  "title": "About AREN",
  "intro": "AREN Athletic represents discipline, presence, and consistency — principles that guide performance in sport and in life.",
  "story": "Founded to create a space where performance training, community, and apparel intersect, AREN is built for individuals who pursue excellence daily. Whether in training, competition, or everyday life, the standard remains the same: show up, do the work, and continue to progress.",
  "values": [
    {
      "title": "Discipline",
      "description": "Commitment to showing up daily and doing the work required to improve."
    },
    {
      "title": "Presence",
      "description": "Focused effort in every session, every run, and every moment of training."
    },
    {
      "title": "Consistency",
      "description": "Progress built through repeated effort over time."
    }
  ]
}